pyc/__init__.py
pyc/git_test.py
pyc/pyc_model.py
predictive_modeling_auto-0.2.1.dist-info/LICENSE
predictive_modeling_auto-0.2.1.dist-info/METADATA
predictive_modeling_auto-0.2.1.dist-info/WHEEL
predictive_modeling_auto-0.2.1.dist-info/top_level.txt
predictive_modeling_auto-0.2.1.dist-info/RECORD
