Metadata-Version: 2.1
Name: predictive-modeling-auto
Version: 0.2.1
Summary: A package for automating predictive modeling tasks using Python
Home-page: https://github.com/ashishs1407/predictive_modeling_auto
Author: Ashish Shimpi
Author-email: a.shimpi93@gmail.com
Project-URL: Source, https://github.com/ashishs1407/predictive_modeling_auto
Project-URL: Tracker, https://github.com/ashishs1407/predictive_modeling_auto/issues
Classifier: Development Status :: 4 - Beta
Classifier: Intended Audience :: Developers
Classifier: Programming Language :: Python :: 3
Classifier: Programming Language :: Python :: 3.8
Classifier: Programming Language :: Python :: 3.9
Classifier: License :: OSI Approved :: MIT License
Requires-Python: >=3.6
License-File: LICENSE
